docs/source/conf.py
numkit/__init__.py
numkit/_version.py
numkit/fitting.py
numkit/integration.py
numkit/observables.py
numkit/timeseries.py
numkit/tests/__init__.py
numkit/tests/test_fitting.py
numkit/tests/test_integration.py
numkit/tests/test_module.py
numkit/tests/test_observables.py
numkit/tests/test_timeseries.py
numkit-1.3.1.dist-info/AUTHORS
numkit-1.3.1.dist-info/LICENSE
numkit-1.3.1.dist-info/METADATA
numkit-1.3.1.dist-info/WHEEL
numkit-1.3.1.dist-info/top_level.txt
numkit-1.3.1.dist-info/RECORD
