Metadata-Version: 2.1
Name: numkit
Version: 1.3.1
Summary: numerical first aid kit
Author-email: Oliver Beckstein <orbeckst@gmail.com>
License: BSD
Project-URL: homepage, https://github.com/Becksteinlab/numkit
Project-URL: documentation, https://numkit.readthedocs.org/
Project-URL: repository, https://github.com/Becksteinlab/numkit
Project-URL: bug-tracker, https://github.com/Becksteinlab/numkit/issues
Classifier: Development Status :: 6 - Mature
Classifier: Environment :: Console
Classifier: Intended Audience :: Science/Research
Classifier: License :: OSI Approved :: BSD License
Classifier: Operating System :: POSIX
Classifier: Operating System :: MacOS :: MacOS X
Classifier: Operating System :: Microsoft :: Windows
Classifier: Programming Language :: Python
Classifier: Programming Language :: Python :: 3.9
Classifier: Programming Language :: Python :: 3.10
Classifier: Programming Language :: Python :: 3.11
Classifier: Programming Language :: Python :: 3.12
Classifier: Topic :: Scientific/Engineering
Classifier: Topic :: Software Development :: Libraries :: Python Modules
Requires-Python: >=3.9
License-File: LICENSE
License-File: AUTHORS
Requires-Dist: numpy>=1.9
Requires-Dist: scipy>=1.0
Provides-Extra: testing
Requires-Dist: pytest; extra == "testing"
